metafora/__init__.py
metafora/common.py
metafora/enums.py
metafora/metar.py
metafora/ml.py
metafora/parser.py
metafora/taf.py
metafora/utils.py
metafora-1.1.1.dist-info/METADATA
metafora-1.1.1.dist-info/WHEEL
metafora-1.1.1.dist-info/top_level.txt
metafora-1.1.1.dist-info/RECORD
